visual_genome/__init__.py
visual_genome/api.py
visual_genome/local.py
visual_genome/models.py
visual_genome/utils.py
visual_genome-1.1.1.dist-info/DESCRIPTION.rst
visual_genome-1.1.1.dist-info/METADATA
visual_genome-1.1.1.dist-info/RECORD
visual_genome-1.1.1.dist-info/WHEEL
visual_genome-1.1.1.dist-info/metadata.json
visual_genome-1.1.1.dist-info/top_level.txt
