Metadata-Version: 2.0
Name: visual-genome
Version: 1.1.1
Summary: A pure python wrapper for the Visual Genome API
Home-page: https://github.com/ranjaykrishna/visual_genome_python_driver
Author: Ranjay Krishna
Author-email: anjaykrishna@gmail.com
License: MIT
Keywords: Spyder,Plugin
Platform: UNKNOWN
Classifier: Development Status :: 4 - Beta
Classifier: Intended Audience :: Developers
Classifier: Intended Audience :: Science/Research
Classifier: License :: OSI Approved :: MIT License
Classifier: Operating System :: MacOS
Classifier: Operating System :: Microsoft :: Windows
Classifier: Operating System :: POSIX :: Linux
Classifier: Programming Language :: Python :: 2.7
Classifier: Programming Language :: Python :: 3.5
Classifier: Programming Language :: Python :: 3.6
Requires-Dist: progressbar2
Requires-Dist: requests
